{
  "info": {
    "name": "Austin-Backend - Complete Live Streaming API v2.0",
    "_postman_id": "austin-backend-live-streaming-complete",
    "description": "Complete Live Streaming API with all verified endpoints: User Auth + User Profile, Admin Auth + Admin Profile, Streaming, Gifts, Polls, Analytics. Production-ready for go-live. VERIFIED: Endpoints audited and matched with actual codebase (auth.route.ts, user.route.ts, admin.route.ts)",
    "schema": "https://schema.getpostman.com/json/collection/v2.1.0/collection.json"
  },
  "item": [
    {
      "name": "1. USER AUTH & PROFILE",
      "item": [
        {
          "name": "1.1 User Authentication",
          "item": [
            {
              "name": "Register (FORM-DATA with image)",
              "request": {
                "method": "POST",
                "header": [],
                "body": {
                  "mode": "formdata",
                  "formdata": [
                    {
                      "key": "name",
                      "value": "John Doe",
                      "type": "text"
                    },
                    {
                      "key": "userName",
                      "value": "johndoe123",
                      "type": "text"
                    },
                    {
                      "key": "email",
                      "value": "john@example.com",
                      "type": "text"
                    },
                    {
                      "key": "password",
                      "value": "password@123",
                      "type": "text"
                    },
                    {
                      "key": "confirmPassword",
                      "value": "password@123",
                      "type": "text"
                    },
                    {
                      "key": "bio",
                      "value": "I love streaming",
                      "type": "text"
                    },
                    {
                      "key": "image",
                      "type": "file",
                      "src": "/path/to/image.jpg"
                    }
                  ]
                },
                "url": {
                  "raw": "{{baseUrl}}/api/v1/auth/register",
                  "host": ["{{baseUrl}}"],
                  "path": ["api", "v1", "auth", "register"]
                }
              }
            },
            {
              "name": "Login",
              "request": {
                "method": "POST",
                "header": [
                  {
                    "key": "Content-Type",
                    "value": "application/json"
                  }
                ],
                "body": {
                  "mode": "raw",
                  "raw": "{\n  \"email\": \"user@example.com\",\n  \"password\": \"password123\"\n}"
                },
                "url": {
                  "raw": "{{baseUrl}}/api/v1/auth/login",
                  "host": ["{{baseUrl}}"],
                  "path": ["api", "v1", "auth", "login"]
                }
              }
            },
            {
              "name": "Refresh Token",
              "request": {
                "method": "POST",
                "header": [],
                "url": {
                  "raw": "{{baseUrl}}/api/v1/auth/refresh-token",
                  "host": ["{{baseUrl}}"],
                  "path": ["api", "v1", "auth", "refresh-token"]
                }
              }
            },
            {
              "name": "Google Login",
              "request": {
                "method": "POST",
                "header": [
                  {
                    "key": "Content-Type",
                    "value": "application/json"
                  }
                ],
                "body": {
                  "mode": "raw",
                  "raw": "{\n  \"token\": \"google_id_token\"\n}"
                },
                "url": {
                  "raw": "{{baseUrl}}/api/v1/auth/google-login",
                  "host": ["{{baseUrl}}"],
                  "path": ["api", "v1", "auth", "google-login"]
                }
              }
            },
            {
              "name": "Apple Login",
              "request": {
                "method": "POST",
                "header": [
                  {
                    "key": "Content-Type",
                    "value": "application/json"
                  }
                ],
                "body": {
                  "mode": "raw",
                  "raw": "{\n  \"token\": \"apple_id_token\"\n}"
                },
                "url": {
                  "raw": "{{baseUrl}}/api/v1/auth/apple-login",
                  "host": ["{{baseUrl}}"],
                  "path": ["api", "v1", "auth", "apple-login"]
                }
              }
            },
            {
              "name": "Verify OTP & Login",
              "request": {
                "method": "POST",
                "header": [
                  {
                    "key": "Content-Type",
                    "value": "application/json"
                  }
                ],
                "body": {
                  "mode": "raw",
                  "raw": "{\n  \"email\": \"user@example.com\",\n  \"otp\": \"123456\"\n}"
                },
                "url": {
                  "raw": "{{baseUrl}}/api/v1/auth/verify-otp",
                  "host": ["{{baseUrl}}"],
                  "path": ["api", "v1", "auth", "verify-otp"]
                }
              }
            },
            {
              "name": "Resend OTP",
              "request": {
                "method": "POST",
                "header": [
                  {
                    "key": "Content-Type",
                    "value": "application/json"
                  }
                ],
                "body": {
                  "mode": "raw",
                  "raw": "{\n  \"email\": \"user@example.com\"\n}"
                },
                "url": {
                  "raw": "{{baseUrl}}/api/v1/auth/resend-otp",
                  "host": ["{{baseUrl}}"],
                  "path": ["api", "v1", "auth", "resend-otp"]
                }
              }
            },
            {
              "name": "Forgot Password",
              "request": {
                "method": "POST",
                "header": [
                  {
                    "key": "Content-Type",
                    "value": "application/json"
                  }
                ],
                "body": {
                  "mode": "raw",
                  "raw": "{\n  \"email\": \"user@example.com\"\n}"
                },
                "url": {
                  "raw": "{{baseUrl}}/api/v1/auth/forget-password",
                  "host": ["{{baseUrl}}"],
                  "path": ["api", "v1", "auth", "forget-password"]
                }
              }
            },
            {
              "name": "Verify Email",
              "request": {
                "method": "POST",
                "header": [
                  {
                    "key": "Content-Type",
                    "value": "application/json"
                  }
                ],
                "body": {
                  "mode": "raw",
                  "raw": "{\n  \"email\": \"user@example.com\",\n  \"oneTimeCode\": 123456\n}"
                },
                "url": {
                  "raw": "{{baseUrl}}/api/v1/auth/verify-email",
                  "host": ["{{baseUrl}}"],
                  "path": ["api", "v1", "auth", "verify-email"]
                }
              }
            },
            {
              "name": "Verify Reset OTP",
              "request": {
                "method": "POST",
                "header": [
                  {
                    "key": "Content-Type",
                    "value": "application/json"
                  }
                ],
                "body": {
                  "mode": "raw",
                  "raw": "{\n  \"email\": \"user@example.com\",\n  \"otp\": \"123456\"\n}"
                },
                "url": {
                  "raw": "{{baseUrl}}/api/v1/auth/verify-reset-otp",
                  "host": ["{{baseUrl}}"],
                  "path": ["api", "v1", "auth", "verify-reset-otp"]
                }
              }
            },
            {
              "name": "Reset Password",
              "request": {
                "method": "POST",
                "header": [
                  {
                    "key": "Content-Type",
                    "value": "application/json"
                  }
                ],
                "body": {
                  "mode": "raw",
                  "raw": "{\n  \"newPassword\": \"newpassword@123\",\n  \"confirmPassword\": \"newpassword@123\"\n}"
                },
                "url": {
                  "raw": "{{baseUrl}}/api/v1/auth/reset-password",
                  "host": ["{{baseUrl}}"],
                  "path": ["api", "v1", "auth", "reset-password"]
                }
              }
            },
            {
              "name": "Change Password (Protected)",
              "request": {
                "method": "POST",
                "header": [
                  {
                    "key": "Authorization",
                    "value": "Bearer {{userToken}}"
                  },
                  {
                    "key": "Content-Type",
                    "value": "application/json"
                  }
                ],
                "body": {
                  "mode": "raw",
                  "raw": "{\n  \"currentPassword\": \"currentpassword123\",\n  \"newPassword\": \"newpassword@123\",\n  \"confirmPassword\": \"newpassword@123\"\n}"
                },
                "url": {
                  "raw": "{{baseUrl}}/api/v1/auth/change-password",
                  "host": ["{{baseUrl}}"],
                  "path": ["api", "v1", "auth", "change-password"]
                }
              }
            }
          ]
        },
        {
          "name": "1.2 User Profile",
          "item": [
            {
              "name": "Get User Profile (Protected)",
              "request": {
                "method": "GET",
                "header": [
                  {
                    "key": "Authorization",
                    "value": "Bearer {{userToken}}"
                  }
                ],
                "url": {
                  "raw": "{{baseUrl}}/api/v1/user/profile",
                  "host": ["{{baseUrl}}"],
                  "path": ["api", "v1", "user", "profile"]
                }
              }
            },
            {
              "name": "Update User Profile (FORM-DATA)",
              "request": {
                "method": "PATCH",
                "header": [
                  {
                    "key": "Authorization",
                    "value": "Bearer {{userToken}}"
                  }
                ],
                "body": {
                  "mode": "formdata",
                  "formdata": [
                    {
                      "key": "data",
                      "value": "{\"name\":\"John Updated\",\"email\":\"newemail@example.com\"}",
                      "type": "text"
                    },
                    {
                      "key": "image",
                      "type": "file",
                      "src": "/path/to/profile.jpg"
                    }
                  ]
                },
                "url": {
                  "raw": "{{baseUrl}}/api/v1/user/profile",
                  "host": ["{{baseUrl}}"],
                  "path": ["api", "v1", "user", "profile"]
                }
              }
            },
            {
              "name": "Delete User Profile (Protected)",
              "request": {
                "method": "DELETE",
                "header": [
                  {
                    "key": "Authorization",
                    "value": "Bearer {{userToken}}"
                  }
                ],
                "url": {
                  "raw": "{{baseUrl}}/api/v1/user/delete",
                  "host": ["{{baseUrl}}"],
                  "path": ["api", "v1", "user", "delete"]
                }
              }
            }
          ]
        }
      ]
    },
    {
      "name": "2. ADMIN AUTH & PROFILE",
      "item": [
        {
          "name": "2.1 Admin Authentication",
          "item": [
            {
              "name": "Admin Login",
              "request": {
                "method": "POST",
                "header": [
                  {
                    "key": "Content-Type",
                    "value": "application/json"
                  }
                ],
                "body": {
                  "mode": "raw",
                  "raw": "{\n  \"email\": \"admin@example.com\",\n  \"password\": \"admin123\"\n}"
                },
                "url": {
                  "raw": "{{baseUrl}}/api/v1/auth/admin/login",
                  "host": ["{{baseUrl}}"],
                  "path": ["api", "v1", "auth", "admin", "login"]
                }
              }
            },
            {
              "name": "Admin Forgot Password",
              "request": {
                "method": "POST",
                "header": [
                  {
                    "key": "Content-Type",
                    "value": "application/json"
                  }
                ],
                "body": {
                  "mode": "raw",
                  "raw": "{\n  \"email\": \"admin@example.com\"\n}"
                },
                "url": {
                  "raw": "{{baseUrl}}/api/v1/auth/admin/forget-password",
                  "host": ["{{baseUrl}}"],
                  "path": ["api", "v1", "auth", "admin", "forget-password"]
                }
              }
            },
            {
              "name": "Admin Verify Reset OTP",
              "request": {
                "method": "POST",
                "header": [
                  {
                    "key": "Content-Type",
                    "value": "application/json"
                  }
                ],
                "body": {
                  "mode": "raw",
                  "raw": "{\n  \"email\": \"admin@example.com\",\n  \"otp\": \"123456\"\n}"
                },
                "url": {
                  "raw": "{{baseUrl}}/api/v1/auth/admin/verify-reset-otp",
                  "host": ["{{baseUrl}}"],
                  "path": ["api", "v1", "auth", "admin", "verify-reset-otp"]
                }
              }
            },
            {
              "name": "Admin Reset Password",
              "request": {
                "method": "POST",
                "header": [
                  {
                    "key": "Content-Type",
                    "value": "application/json"
                  }
                ],
                "body": {
                  "mode": "raw",
                  "raw": "{\n  \"email\": \"admin@example.com\",\n  \"otp\": \"123456\",\n  \"newPassword\": \"newpassword123\"\n}"
                },
                "url": {
                  "raw": "{{baseUrl}}/api/v1/auth/admin/reset-password",
                  "host": ["{{baseUrl}}"],
                  "path": ["api", "v1", "auth", "admin", "reset-password"]
                }
              }
            },
            {
              "name": "Admin Change Password (Protected)",
              "request": {
                "method": "PATCH",
                "header": [
                  {
                    "key": "Authorization",
                    "value": "Bearer {{adminToken}}"
                  },
                  {
                    "key": "Content-Type",
                    "value": "application/json"
                  }
                ],
                "body": {
                  "mode": "raw",
                  "raw": "{\n  \"oldPassword\": \"currentpassword\",\n  \"newPassword\": \"newpassword123\"\n}"
                },
                "url": {
                  "raw": "{{baseUrl}}/api/v1/auth/admin/change-password",
                  "host": ["{{baseUrl}}"],
                  "path": ["api", "v1", "auth", "admin", "change-password"]
                }
              }
            },
            {
              "name": "Admin Resend OTP",
              "request": {
                "method": "POST",
                "header": [
                  {
                    "key": "Content-Type",
                    "value": "application/json"
                  }
                ],
                "body": {
                  "mode": "raw",
                  "raw": "{\n  \"email\": \"admin@example.com\"\n}"
                },
                "url": {
                  "raw": "{{baseUrl}}/api/v1/auth/admin/resend-otp",
                  "host": ["{{baseUrl}}"],
                  "path": ["api", "v1", "auth", "admin", "resend-otp"]
                }
              }
            }
          ]
        },
        {
          "name": "2.2 Admin Profile & Management",
          "item": [
            {
              "name": "Get My Admin Profile (Protected)",
              "request": {
                "method": "GET",
                "header": [
                  {
                    "key": "Authorization",
                    "value": "Bearer {{adminToken}}"
                  }
                ],
                "url": {
                  "raw": "{{baseUrl}}/api/v1/admin/profile",
                  "host": ["{{baseUrl}}"],
                  "path": ["api", "v1", "admin", "profile"]
                }
              }
            },
            {
              "name": "Get All Admins (SUPER_ADMIN)",
              "request": {
                "method": "GET",
                "header": [
                  {
                    "key": "Authorization",
                    "value": "Bearer {{adminToken}}"
                  }
                ],
                "url": {
                  "raw": "{{baseUrl}}/api/v1/admin/get-admin",
                  "host": ["{{baseUrl}}"],
                  "path": ["api", "v1", "admin", "get-admin"]
                }
              }
            },
            {
              "name": "Create Admin (SUPER_ADMIN)",
              "request": {
                "method": "POST",
                "header": [
                  {
                    "key": "Authorization",
                    "value": "Bearer {{adminToken}}"
                  },
                  {
                    "key": "Content-Type",
                    "value": "application/json"
                  }
                ],
                "body": {
                  "mode": "raw",
                  "raw": "{\n  \"name\": \"New Admin\",\n  \"email\": \"newadmin@example.com\",\n  \"password\": \"adminpassword\",\n  \"role\": \"admin\"\n}"
                },
                "url": {
                  "raw": "{{baseUrl}}/api/v1/admin/create-admin",
                  "host": ["{{baseUrl}}"],
                  "path": ["api", "v1", "admin", "create-admin"]
                }
              }
            },
            {
              "name": "Delete Admin (SUPER_ADMIN)",
              "request": {
                "method": "DELETE",
                "header": [
                  {
                    "key": "Authorization",
                    "value": "Bearer {{adminToken}}"
                  }
                ],
                "url": {
                  "raw": "{{baseUrl}}/api/v1/admin/{{adminId}}",
                  "host": ["{{baseUrl}}"],
                  "path": ["api", "v1", "admin", "{{adminId}}"]
                }
              }
            }
          ]
        }
      ]
    },
    {
      "name": "3. CATEGORIES",
      "item": [
        {
          "name": "Get All Categories",
          "request": {
            "method": "GET",
            "header": [],
            "url": {
              "raw": "{{baseUrl}}/api/v1/category?page=1&limit=20",
              "host": ["{{baseUrl}}"],
              "path": ["api", "v1", "category"],
              "query": [
                {
                  "key": "page",
                  "value": "1"
                },
                {
                  "key": "limit",
                  "value": "20"
                }
              ]
            }
          }
        },
        {
          "name": "Get Category by ID",
          "request": {
            "method": "GET",
            "header": [],
            "url": {
              "raw": "{{baseUrl}}/api/v1/category/{{categoryId}}",
              "host": ["{{baseUrl}}"],
              "path": ["api", "v1", "category", "{{categoryId}}"]
            }
          }
        },
        {
          "name": "Create Category (Admin)",
          "request": {
            "method": "POST",
            "header": [
              {
                "key": "Authorization",
                "value": "Bearer {{adminToken}}"
              },
              {
                "key": "Content-Type",
                "value": "application/json"
              }
            ],
            "body": {
              "mode": "raw",
              "raw": "{\n  \"title\": \"Gaming\",\n  \"description\": \"Gaming streams\",\n  \"icon\": \"gaming-icon\",\n  \"isActive\": true\n}"
            },
            "url": {
              "raw": "{{baseUrl}}/api/v1/category",
              "host": ["{{baseUrl}}"],
              "path": ["api", "v1", "category"]
            }
          }
        },
        {
          "name": "Update Category (Admin)",
          "request": {
            "method": "PATCH",
            "header": [
              {
                "key": "Authorization",
                "value": "Bearer {{adminToken}}"
              },
              {
                "key": "Content-Type",
                "value": "application/json"
              }
            ],
            "body": {
              "mode": "raw",
              "raw": "{\n  \"title\": \"Updated Gaming\",\n  \"isActive\": true\n}"
            },
            "url": {
              "raw": "{{baseUrl}}/api/v1/category/{{categoryId}}",
              "host": ["{{baseUrl}}"],
              "path": ["api", "v1", "category", "{{categoryId}}"]
            }
          }
        },
        {
          "name": "Delete Category (Admin)",
          "request": {
            "method": "DELETE",
            "header": [
              {
                "key": "Authorization",
                "value": "Bearer {{adminToken}}"
              }
            ],
            "url": {
              "raw": "{{baseUrl}}/api/v1/category/{{categoryId}}",
              "host": ["{{baseUrl}}"],
              "path": ["api", "v1", "category", "{{categoryId}}"]
            }
          }
        }
      ]
    },
    {
      "name": "4. STREAM MANAGEMENT",
      "item": [
        {
          "name": "Start Stream (FORM-DATA with banner)",
          "request": {
            "method": "POST",
            "header": [
              {
                "key": "Authorization",
                "value": "Bearer {{userToken}}"
              }
            ],
            "body": {
              "mode": "formdata",
              "formdata": [
                {
                  "key": "title",
                  "value": "Epic Gaming Session",
                  "type": "text"
                },
                {
                  "key": "description",
                  "value": "Playing the latest games",
                  "type": "text"
                },
                {
                  "key": "category",
                  "value": "{{categoryId}}",
                  "type": "text"
                },
                {
                  "key": "contentRating",
                  "value": "PG-13",
                  "type": "text"
                },
                {
                  "key": "banner",
                  "type": "file",
                  "src": "/path/to/banner.jpg"
                },
                {
                  "key": "bannerPosition",
                  "value": "top",
                  "type": "text"
                },
                {
                  "key": "visibility",
                  "value": "public",
                  "type": "text"
                },
                {
                  "key": "allowComments",
                  "value": "true",
                  "type": "text"
                },
                {
                  "key": "allowGifts",
                  "value": "true",
                  "type": "text"
                },
                {
                  "key": "enablePolls",
                  "value": "true",
                  "type": "text"
                },
                {
                  "key": "enableAdBanners",
                  "value": "false",
                  "type": "text"
                },
                {
                  "key": "isAgeRestricted",
                  "value": "false",
                  "type": "text"
                },
                {
                  "key": "isRecordingEnabled",
                  "value": "true",
                  "type": "text"
                },
                {
                  "key": "tags",
                  "value": "gaming,live,fun",
                  "type": "text"
                }
              ]
            },
            "url": {
              "raw": "{{baseUrl}}/api/v1/stream/start",
              "host": ["{{baseUrl}}"],
              "path": ["api", "v1", "stream", "start"]
            }
          }
        },
        {
          "name": "Get Live Streams",
          "request": {
            "method": "GET",
            "header": [],
            "url": {
              "raw": "{{baseUrl}}/api/v1/stream/live?page=1&limit=20",
              "host": ["{{baseUrl}}"],
              "path": ["api", "v1", "stream", "live"],
              "query": [
                {
                  "key": "page",
                  "value": "1"
                },
                {
                  "key": "limit",
                  "value": "20"
                }
              ]
            }
          }
        },
        {
          "name": "Search Streams",
          "request": {
            "method": "GET",
            "header": [],
            "url": {
              "raw": "{{baseUrl}}/api/v1/stream/search?q=gaming",
              "host": ["{{baseUrl}}"],
              "path": ["api", "v1", "stream", "search"],
              "query": [
                {
                  "key": "q",
                  "value": "gaming"
                }
              ]
            }
          }
        },
        {
          "name": "Get Stream Details",
          "request": {
            "method": "GET",
            "header": [],
            "url": {
              "raw": "{{baseUrl}}/api/v1/stream/{{streamId}}",
              "host": ["{{baseUrl}}"],
              "path": ["api", "v1", "stream", "{{streamId}}"]
            }
          }
        },
        {
          "name": "Get Streamer History",
          "request": {
            "method": "GET",
            "header": [],
            "url": {
              "raw": "{{baseUrl}}/api/v1/stream/streamer/{{userId}}/history?page=1&limit=20",
              "host": ["{{baseUrl}}"],
              "path": ["api", "v1", "stream", "streamer", "{{userId}}", "history"],
              "query": [
                {
                  "key": "page",
                  "value": "1"
                },
                {
                  "key": "limit",
                  "value": "20"
                }
              ]
            }
          }
        },
        {
          "name": "Join Stream (Get Agora Token)",
          "request": {
            "method": "POST",
            "header": [
              {
                "key": "Authorization",
                "value": "Bearer {{userToken}}"
              }
            ],
            "url": {
              "raw": "{{baseUrl}}/api/v1/stream/{{streamId}}/join",
              "host": ["{{baseUrl}}"],
              "path": ["api", "v1", "stream", "{{streamId}}", "join"]
            }
          }
        },
        {
          "name": "Leave Stream",
          "request": {
            "method": "POST",
            "header": [
              {
                "key": "Authorization",
                "value": "Bearer {{userToken}}"
              }
            ],
            "url": {
              "raw": "{{baseUrl}}/api/v1/stream/{{streamId}}/leave",
              "host": ["{{baseUrl}}"],
              "path": ["api", "v1", "stream", "{{streamId}}", "leave"]
            }
          }
        },
        {
          "name": "Like Stream",
          "request": {
            "method": "POST",
            "header": [
              {
                "key": "Authorization",
                "value": "Bearer {{userToken}}"
              }
            ],
            "url": {
              "raw": "{{baseUrl}}/api/v1/stream/{{streamId}}/like",
              "host": ["{{baseUrl}}"],
              "path": ["api", "v1", "stream", "{{streamId}}", "like"]
            }
          }
        },
        {
          "name": "Send Chat Message",
          "request": {
            "method": "POST",
            "header": [
              {
                "key": "Authorization",
                "value": "Bearer {{userToken}}"
              },
              {
                "key": "Content-Type",
                "value": "application/json"
              }
            ],
            "body": {
              "mode": "raw",
              "raw": "{\n  \"content\": \"Amazing stream! 🔥\",\n  \"type\": \"text\"\n}"
            },
            "url": {
              "raw": "{{baseUrl}}/api/v1/stream/{{streamId}}/chat",
              "host": ["{{baseUrl}}"],
              "path": ["api", "v1", "stream", "{{streamId}}", "chat"]
            }
          }
        },
        {
          "name": "Update Stream Settings",
          "request": {
            "method": "PUT",
            "header": [
              {
                "key": "Authorization",
                "value": "Bearer {{userToken}}"
              },
              {
                "key": "Content-Type",
                "value": "application/json"
              }
            ],
            "body": {
              "mode": "raw",
              "raw": "{\n  \"title\": \"Updated Title\",\n  \"allowComments\": true,\n  \"allowGifts\": true\n}"
            },
            "url": {
              "raw": "{{baseUrl}}/api/v1/stream/{{streamId}}/settings",
              "host": ["{{baseUrl}}"],
              "path": ["api", "v1", "stream", "{{streamId}}", "settings"]
            }
          }
        },
        {
          "name": "Toggle Stream Controls",
          "request": {
            "method": "PUT",
            "header": [
              {
                "key": "Authorization",
                "value": "Bearer {{userToken}}"
              },
              {
                "key": "Content-Type",
                "value": "application/json"
              }
            ],
            "body": {
              "mode": "raw",
              "raw": "{\n  \"cameraOn\": true,\n  \"micOn\": true\n}"
            },
            "url": {
              "raw": "{{baseUrl}}/api/v1/stream/{{streamId}}/controls",
              "host": ["{{baseUrl}}"],
              "path": ["api", "v1", "stream", "{{streamId}}", "controls"]
            }
          }
        },
        {
          "name": "Get Stream Analytics",
          "request": {
            "method": "GET",
            "header": [
              {
                "key": "Authorization",
                "value": "Bearer {{userToken}}"
              }
            ],
            "url": {
              "raw": "{{baseUrl}}/api/v1/stream/{{streamId}}/analytics",
              "host": ["{{baseUrl}}"],
              "path": ["api", "v1", "stream", "{{streamId}}", "analytics"]
            }
          }
        },
        {
          "name": "End Stream",
          "request": {
            "method": "POST",
            "header": [
              {
                "key": "Authorization",
                "value": "Bearer {{userToken}}"
              }
            ],
            "url": {
              "raw": "{{baseUrl}}/api/v1/stream/{{streamId}}/end",
              "host": ["{{baseUrl}}"],
              "path": ["api", "v1", "stream", "{{streamId}}", "end"]
            }
          }
        }
      ]
    },
    {
      "name": "5. GIFTS",
      "item": [
        {
          "name": "Get All Gifts",
          "request": {
            "method": "GET",
            "header": [],
            "url": {
              "raw": "{{baseUrl}}/api/v1/gift",
              "host": ["{{baseUrl}}"],
              "path": ["api", "v1", "gift"]
            }
          }
        },
        {
          "name": "Get Gifts by Category",
          "request": {
            "method": "GET",
            "header": [],
            "url": {
              "raw": "{{baseUrl}}/api/v1/gift/category/{{categoryName}}",
              "host": ["{{baseUrl}}"],
              "path": ["api", "v1", "gift", "category", "{{categoryName}}"]
            }
          }
        },
        {
          "name": "Get Gift by ID",
          "request": {
            "method": "GET",
            "header": [],
            "url": {
              "raw": "{{baseUrl}}/api/v1/gift/{{giftId}}",
              "host": ["{{baseUrl}}"],
              "path": ["api", "v1", "gift", "{{giftId}}"]
            }
          }
        },
        {
          "name": "Create Gift (Admin)",
          "request": {
            "method": "POST",
            "header": [
              {
                "key": "Authorization",
                "value": "Bearer {{adminToken}}"
              },
              {
                "key": "Content-Type",
                "value": "application/json"
              }
            ],
            "body": {
              "mode": "raw",
              "raw": "{\n  \"name\": \"Heart\",\n  \"description\": \"Show your love\",\n  \"image\": \"https://example.com/heart.png\",\n  \"animation\": \"https://example.com/heart.json\",\n  \"price\": 10,\n  \"category\": \"love\",\n  \"isActive\": true\n}"
            },
            "url": {
              "raw": "{{baseUrl}}/api/v1/gift",
              "host": ["{{baseUrl}}"],
              "path": ["api", "v1", "gift"]
            }
          }
        },
        {
          "name": "Update Gift (Admin)",
          "request": {
            "method": "PUT",
            "header": [
              {
                "key": "Authorization",
                "value": "Bearer {{adminToken}}"
              },
              {
                "key": "Content-Type",
                "value": "application/json"
              }
            ],
            "body": {
              "mode": "raw",
              "raw": "{\n  \"name\": \"Updated Heart\",\n  \"price\": 15\n}"
            },
            "url": {
              "raw": "{{baseUrl}}/api/v1/gift/{{giftId}}",
              "host": ["{{baseUrl}}"],
              "path": ["api", "v1", "gift", "{{giftId}}"]
            }
          }
        },
        {
          "name": "Delete Gift (Admin)",
          "request": {
            "method": "DELETE",
            "header": [
              {
                "key": "Authorization",
                "value": "Bearer {{adminToken}}"
              }
            ],
            "url": {
              "raw": "{{baseUrl}}/api/v1/gift/{{giftId}}",
              "host": ["{{baseUrl}}"],
              "path": ["api", "v1", "gift", "{{giftId}}"]
            }
          }
        },
        {
          "name": "Send Gift to Stream",
          "request": {
            "method": "POST",
            "header": [
              {
                "key": "Authorization",
                "value": "Bearer {{userToken}}"
              },
              {
                "key": "Content-Type",
                "value": "application/json"
              }
            ],
            "body": {
              "mode": "raw",
              "raw": "{\n  \"gift\": \"{{giftId}}\",\n  \"quantity\": 1,\n  \"message\": \"Great stream!\",\n  \"isAnonymous\": false\n}"
            },
            "url": {
              "raw": "{{baseUrl}}/api/v1/gift/send/{{streamId}}",
              "host": ["{{baseUrl}}"],
              "path": ["api", "v1", "gift", "send", "{{streamId}}"]
            }
          }
        },
        {
          "name": "Get Stream Gifts",
          "request": {
            "method": "GET",
            "header": [
              {
                "key": "Authorization",
                "value": "Bearer {{userToken}}"
              }
            ],
            "url": {
              "raw": "{{baseUrl}}/api/v1/gift/stream/{{streamId}}/list",
              "host": ["{{baseUrl}}"],
              "path": ["api", "v1", "gift", "stream", "{{streamId}}", "list"]
            }
          }
        },
        {
          "name": "Get Streamer Received Gifts",
          "request": {
            "method": "GET",
            "header": [
              {
                "key": "Authorization",
                "value": "Bearer {{userToken}}"
              }
            ],
            "url": {
              "raw": "{{baseUrl}}/api/v1/gift/streamer/received",
              "host": ["{{baseUrl}}"],
              "path": ["api", "v1", "gift", "streamer", "received"]
            }
          }
        }
      ]
    },
    {
      "name": "6. POLLS",
      "item": [
        {
          "name": "Create Poll (Streamer)",
          "request": {
            "method": "POST",
            "header": [
              {
                "key": "Authorization",
                "value": "Bearer {{userToken}}"
              },
              {
                "key": "Content-Type",
                "value": "application/json"
              }
            ],
            "body": {
              "mode": "raw",
              "raw": "{\n  \"question\": \"What game should I play next?\",\n  \"options\": [\"Valorant\", \"CS:GO\", \"Apex Legends\"],\n  \"duration\": 300,\n  \"allowMultipleVotes\": false\n}"
            },
            "url": {
              "raw": "{{baseUrl}}/api/v1/poll/stream/{{streamId}}/create",
              "host": ["{{baseUrl}}"],
              "path": ["api", "v1", "poll", "stream", "{{streamId}}", "create"]
            }
          }
        },
        {
          "name": "Vote on Poll",
          "request": {
            "method": "POST",
            "header": [
              {
                "key": "Authorization",
                "value": "Bearer {{userToken}}"
              },
              {
                "key": "Content-Type",
                "value": "application/json"
              }
            ],
            "body": {
              "mode": "raw",
              "raw": "{\n  \"optionIndex\": 0\n}"
            },
            "url": {
              "raw": "{{baseUrl}}/api/v1/poll/{{pollId}}/vote",
              "host": ["{{baseUrl}}"],
              "path": ["api", "v1", "poll", "{{pollId}}", "vote"]
            }
          }
        },
        {
          "name": "Get Poll Results",
          "request": {
            "method": "GET",
            "header": [],
            "url": {
              "raw": "{{baseUrl}}/api/v1/poll/{{pollId}}/results",
              "host": ["{{baseUrl}}"],
              "path": ["api", "v1", "poll", "{{pollId}}", "results"]
            }
          }
        },
        {
          "name": "Get Active Poll",
          "request": {
            "method": "GET",
            "header": [],
            "url": {
              "raw": "{{baseUrl}}/api/v1/poll/stream/{{streamId}}/active",
              "host": ["{{baseUrl}}"],
              "path": ["api", "v1", "poll", "stream", "{{streamId}}", "active"]
            }
          }
        },
        {
          "name": "Get All Stream Polls",
          "request": {
            "method": "GET",
            "header": [],
            "url": {
              "raw": "{{baseUrl}}/api/v1/poll/stream/{{streamId}}/all",
              "host": ["{{baseUrl}}"],
              "path": ["api", "v1", "poll", "stream", "{{streamId}}", "all"]
            }
          }
        },
        {
          "name": "End Poll (Streamer)",
          "request": {
            "method": "POST",
            "header": [
              {
                "key": "Authorization",
                "value": "Bearer {{userToken}}"
              }
            ],
            "url": {
              "raw": "{{baseUrl}}/api/v1/poll/{{pollId}}/end",
              "host": ["{{baseUrl}}"],
              "path": ["api", "v1", "poll", "{{pollId}}", "end"]
            }
          }
        },
        {
          "name": "Delete Poll (Streamer)",
          "request": {
            "method": "DELETE",
            "header": [
              {
                "key": "Authorization",
                "value": "Bearer {{userToken}}"
              }
            ],
            "url": {
              "raw": "{{baseUrl}}/api/v1/poll/{{pollId}}",
              "host": ["{{baseUrl}}"],
              "path": ["api", "v1", "poll", "{{pollId}}"]
            }
          }
        }
      ]
    },
    {
      "name": "7. ANALYTICS DASHBOARD",
      "item": [
        {
          "name": "Platform Analytics (Admin)",
          "request": {
            "method": "GET",
            "header": [
              {
                "key": "Authorization",
                "value": "Bearer {{adminToken}}"
              }
            ],
            "url": {
              "raw": "{{baseUrl}}/api/v1/analytics/platform?startDate=2026-01-01&endDate=2026-01-31",
              "host": ["{{baseUrl}}"],
              "path": ["api", "v1", "analytics", "platform"],
              "query": [
                {
                  "key": "startDate",
                  "value": "2026-01-01"
                },
                {
                  "key": "endDate",
                  "value": "2026-01-31"
                }
              ]
            }
          }
        },
        {
          "name": "Real-time Analytics",
          "request": {
            "method": "GET",
            "header": [],
            "url": {
              "raw": "{{baseUrl}}/api/v1/analytics/realtime",
              "host": ["{{baseUrl}}"],
              "path": ["api", "v1", "analytics", "realtime"]
            }
          }
        },
        {
          "name": "Streamer Analytics",
          "request": {
            "method": "GET",
            "header": [
              {
                "key": "Authorization",
                "value": "Bearer {{userToken}}"
              }
            ],
            "url": {
              "raw": "{{baseUrl}}/api/v1/analytics/streamer/{{userId}}",
              "host": ["{{baseUrl}}"],
              "path": ["api", "v1", "analytics", "streamer", "{{userId}}"]
            }
          }
        },
        {
          "name": "My Dashboard",
          "request": {
            "method": "GET",
            "header": [
              {
                "key": "Authorization",
                "value": "Bearer {{userToken}}"
              }
            ],
            "url": {
              "raw": "{{baseUrl}}/api/v1/analytics/my-dashboard",
              "host": ["{{baseUrl}}"],
              "path": ["api", "v1", "analytics", "my-dashboard"]
            }
          }
        },
        {
          "name": "Category Analytics",
          "request": {
            "method": "GET",
            "header": [],
            "url": {
              "raw": "{{baseUrl}}/api/v1/analytics/category/{{categoryId}}",
              "host": ["{{baseUrl}}"],
              "path": ["api", "v1", "analytics", "category", "{{categoryId}}"]
            }
          }
        },
        {
          "name": "Comparison Analytics",
          "request": {
            "method": "GET",
            "header": [
              {
                "key": "Authorization",
                "value": "Bearer {{userToken}}"
              }
            ],
            "url": {
              "raw": "{{baseUrl}}/api/v1/analytics/comparison",
              "host": ["{{baseUrl}}"],
              "path": ["api", "v1", "analytics", "comparison"]
            }
          }
        }
      ]
    }
  ],
  "variable": [
    {
      "key": "baseUrl",
      "value": "http://65.1.20.111:5000",
      "type": "string"
    },
    {
      "key": "userToken",
      "value": "",
      "type": "string"
    },
    {
      "key": "adminToken",
      "value": "",
      "type": "string"
    },
    {
      "key": "categoryId",
      "value": "",
      "type": "string"
    },
    {
      "key": "categoryName",
      "value": "",
      "type": "string"
    },
    {
      "key": "streamId",
      "value": "",
      "type": "string"
    },
    {
      "key": "userId",
      "value": "",
      "type": "string"
    },
    {
      "key": "adminId",
      "value": "",
      "type": "string"
    },
    {
      "key": "giftId",
      "value": "",
      "type": "string"
    },
    {
      "key": "pollId",
      "value": "",
      "type": "string"
    }
  ]
}
